llm_mcp/__init__.py
llm_mcp/client.py
llm_mcp/commands.py
llm_mcp/commands_tools.py
llm_mcp/config.py
llm_mcp/server_manager.py
llm_mcp/tool_provider.py
llm_mcp/utils.py
llm_mcp_cli-1.0.5.dist-info/licenses/LICENSE
llm_mcp_cli-1.0.5.dist-info/METADATA
llm_mcp_cli-1.0.5.dist-info/WHEEL
llm_mcp_cli-1.0.5.dist-info/entry_points.txt
llm_mcp_cli-1.0.5.dist-info/top_level.txt
llm_mcp_cli-1.0.5.dist-info/RECORD
