Metadata-Version: 2.4
Name: llm-mcp-cli
Version: 1.0.5
Summary: LLM plugin for Model Context Protocol (MCP) integration
Author-email: Eugene Pyvovarov <eugene.pyvovarov@gmail.com>
License: Apache-2.0
Project-URL: Homepage, https://github.com/eugenepyvovarov/llm-mcp
Project-URL: Repository, https://github.com/eugenepyvovarov/llm-mcp
Project-URL: Documentation, https://github.com/eugenepyvovarov/llm-mcp#readme
Keywords: llm,mcp,model-context-protocol,plugin
Classifier: Development Status :: 4 - Beta
Classifier: Intended Audience :: Developers
Classifier: License :: OSI Approved :: Apache Software License
Classifier: Programming Language :: Python :: 3
Classifier: Programming Language :: Python :: 3.11
Classifier: Programming Language :: Python :: 3.12
Classifier: Programming Language :: Python :: 3.13
Requires-Python: >=3.11
License-File: LICENSE
Requires-Dist: llm>=0.27.1
Requires-Dist: pydantic>=2.11.7
Requires-Dist: click>=8.2.1
Requires-Dist: mcp>=1.13.1
Provides-Extra: dev
Requires-Dist: pytest>=8.4.1; extra == "dev"
Requires-Dist: pytest-asyncio>=1.1.0; extra == "dev"
Requires-Dist: black>=25.1.0; extra == "dev"
Requires-Dist: ruff>=0.12.10; extra == "dev"
Dynamic: license-file
